MANIFEST.in
setup.py
redwine/__init__.py
redwine/admin.py
redwine/forms.py
redwine/models.py
redwine/settings.py
redwine/urls.py
redwine/views.py
redwine/wsgi.py
redwine.egg-info/PKG-INFO
redwine.egg-info/SOURCES.txt
redwine.egg-info/dependency_links.txt
redwine.egg-info/top_level.txt
redwine/static/css/bootstrap-theme.css
redwine/static/css/bootstrap-theme.min.css
redwine/static/css/bootstrap.css
redwine/static/css/bootstrap.min.css
redwine/static/css/lol.js
redwine/static/css/redwine.css
redwine/static/fonts/glyphicons-halflings-regular.eot
redwine/static/fonts/glyphicons-halflings-regular.svg
redwine/static/fonts/glyphicons-halflings-regular.ttf
redwine/static/fonts/glyphicons-halflings-regular.woff
redwine/static/img/beer.png
redwine/static/img/cake.png
redwine/static/img/halfwine.png
redwine/static/img/nyan.gif
redwine/static/img/wine.png
redwine/static/js/bootstrap.js
redwine/static/js/bootstrap.min.js
redwine/static/js/jquery.filtertable.min.js
redwine/static/js/jquery.tablesorter.min.js
redwine/static/js/list.min.js
redwine/static/js/redwine.js
redwine/templates/base.html
redwine/templates/index.html
redwine/templatetags/__init__.py
redwine/templatetags/__init__.pyc
redwine/templatetags/filters.py
redwine/templatetags/filters.pyc